temnanoc_iq/__init__.py
temnanoc_iq-1.0.1.dist-info/METADATA
temnanoc_iq-1.0.1.dist-info/WHEEL
temnanoc_iq-1.0.1.dist-info/top_level.txt
temnanoc_iq-1.0.1.dist-info/RECORD
