Metadata-Version: 2.1
Name: temnanoc-iq
Version: 1.0.1
Summary: Temnanoc's iq.
Author: mqchinee
Keywords: random,python,eightball
Classifier: Development Status :: 1 - Planning
Classifier: Intended Audience :: Developers
Classifier: Programming Language :: Python :: 3
Classifier: Operating System :: Unix
Classifier: Operating System :: MacOS :: MacOS X
Classifier: Operating System :: Microsoft :: Windows
